{"success":true,"orders":[{"id":"ORD-20251224-29F2A02E","machine_id":"VM01","slot_id":1,"product_id":1,"quantity":1,"total_amount":5000,"status":"DISPENSING","payment_method":"QRIS","payment_url":"https://app.sandbox.midtrans.com/snap/v4/redirection/f2433152-949a-4af8-ada8-e0be8e36eafd","payment_token":"f2433152-949a-4af8-ada8-e0be8e36eafd","expires_at":"2025-12-24T10:57:10.071+00:00","paid_at":"2025-12-24T10:43:10.019+00:00","dispensed_at":null,"customer_phone":null,"notes":null,"created_at":"2025-12-24T10:42:10.797388+00:00","updated_at":"2025-12-24T10:43:11.467415+00:00","payments":[{"status":"PENDING","payment_type":"midtrans"}]},{"id":"ORD-20251224-BC9FEA28","machine_id":"VM01","slot_id":1,"product_id":1,"quantity":2,"total_amount":10000,"status":"PENDING","payment_method":"QRIS","payment_url":"https://app.sandbox.midtrans.com/snap/v4/redirection/4a684f83-6e85-4b5b-949d-7342e42db4e2","payment_token":"4a684f83-6e85-4b5b-949d-7342e42db4e2","expires_at":"2025-12-24T10:49:52.029+00:00","paid_at":null,"dispensed_at":null,"customer_phone":null,"notes":null,"created_at":"2025-12-24T10:34:52.739503+00:00","updated_at":"2025-12-24T10:35:00.625792+00:00","payments":[{"status":"PENDING","payment_type":"midtrans"}]},{"id":"ORD-20251224-49F07D12","machine_id":"VM01","slot_id":1,"product_id":1,"quantity":1,"total_amount":5000,"status":"PENDING","payment_method":"QRIS","payment_url":"https://app.sandbox.midtrans.com/snap/v4/redirection/b4eb3ed1-4332-400b-b3c6-38b73bdf5ba6","payment_token":"b4eb3ed1-4332-400b-b3c6-38b73bdf5ba6","expires_at":"2025-12-24T10:30:39.234+00:00","paid_at":null,"dispensed_at":null,"customer_phone":null,"notes":null,"created_at":"2025-12-24T10:15:39.921518+00:00","updated_at":"2025-12-24T10:16:10.128967+00:00","payments":[{"status":"PENDING","payment_type":"qris"}]},{"id":"ORD-20251224-8F0D56D1","machine_id":"VM01","slot_id":1,"product_id":1,"quantity":1,"total_amount":5000,"status":"PENDING","payment_method":"QRIS","payment_url":"https://app.sandbox.midtrans.com/snap/v4/redirection/751ba909-87f2-4740-8ec4-be6e8da39018","payment_token":"751ba909-87f2-4740-8ec4-be6e8da39018","expires_at":"2025-12-24T10:30:31.898+00:00","paid_at":null,"dispensed_at":null,"customer_phone":null,"notes":null,"created_at":"2025-12-24T10:15:32.603479+00:00","updated_at":"2025-12-24T10:15:34.792298+00:00","payments":[{"status":"PENDING","payment_type":"midtrans"}]},{"id":"ORD-20251224-C32209EF","machine_id":"VM01","slot_id":1,"product_id":1,"quantity":1,"total_amount":5000,"status":"PENDING","payment_method":"QRIS","payment_url":"midtrans://payment/ORD-20251224-C32209EF","payment_token":"33bcfc1f-ffc0-4b5a-a0a6-70fe89aec061","expires_at":"2025-12-24T10:30:27.069+00:00","paid_at":null,"dispensed_at":null,"customer_phone":null,"notes":null,"created_at":"2025-12-24T10:15:27.783535+00:00","updated_at":"2025-12-24T10:15:27.783535+00:00","payments":[{"status":"PENDING","payment_type":"qris"}]},{"id":"ORD-20251224-48352448","machine_id":"VM01","slot_id":1,"product_id":1,"quantity":1,"total_amount":5000,"status":"PENDING","payment_method":"QRIS","payment_url":"midtrans://payment/ORD-20251224-48352448","payment_token":"32ccdab1-8cf7-477e-8b8e-b07b6cbd9c03","expires_at":"2025-12-24T10:27:31.474+00:00","paid_at":null,"dispensed_at":null,"customer_phone":null,"notes":null,"created_at":"2025-12-24T10:12:32.154886+00:00","updated_at":"2025-12-24T10:12:32.154886+00:00","payments":[{"status":"PENDING","payment_type":"qris"}]},{"id":"ORD-20251224-24A308C6","machine_id":"VM01","slot_id":1,"product_id":1,"quantity":1,"total_amount":5000,"status":"PENDING","payment_method":"QRIS","payment_url":"midtrans://payment/ORD-20251224-24A308C6","payment_token":"db912109-9572-4a64-b007-cad366572ded","expires_at":"2025-12-24T10:27:05.329+00:00","paid_at":null,"dispensed_at":null,"customer_phone":null,"notes":null,"created_at":"2025-12-24T10:12:06.030876+00:00","updated_at":"2025-12-24T10:12:06.030876+00:00","payments":[{"status":"PENDING","payment_type":"midtrans"}]},{"id":"ORD-20251224-41535B5F","machine_id":"VM01","slot_id":2,"product_id":2,"quantity":1,"total_amount":3000,"status":"DISPENSING","payment_method":"QRIS","payment_url":"https://app.sandbox.midtrans.com/snap/v4/redirection/1c394d59-ea6a-4100-8095-ef9398023eef","payment_token":"1c394d59-ea6a-4100-8095-ef9398023eef","expires_at":"2025-12-24T01:19:47.059+00:00","paid_at":"2025-12-24T01:05:09.835+00:00","dispensed_at":null,"customer_phone":null,"notes":null,"created_at":"2025-12-24T01:04:47.388987+00:00","updated_at":"2025-12-24T01:05:10.943406+00:00","payments":[{"status":"PENDING","payment_type":"midtrans"}]},{"id":"ORD-20251224-4CB765A1","machine_id":"VM01","slot_id":1,"product_id":1,"quantity":1,"total_amount":5000,"status":"DISPENSING","payment_method":"QRIS","payment_url":"https://app.sandbox.midtrans.com/snap/v4/redirection/1bcaab74-e7d1-4fe3-8250-865e32d7aef6","payment_token":"1bcaab74-e7d1-4fe3-8250-865e32d7aef6","expires_at":"2025-12-24T01:01:41.782+00:00","paid_at":"2025-12-24T01:04:10.509+00:00","dispensed_at":null,"customer_phone":null,"notes":null,"created_at":"2025-12-24T00:46:42.143874+00:00","updated_at":"2025-12-24T01:04:11.743235+00:00","payments":[{"status":"PENDING","payment_type":"midtrans"}]},{"id":"ORD-20251224-02848748","machine_id":"VM01","slot_id":1,"product_id":1,"quantity":1,"total_amount":5000,"status":"PENDING","payment_method":"QRIS","payment_url":"https://app.sandbox.midtrans.com/snap/v4/redirection/d8fab905-a349-4731-b4e3-dcca75de9422","payment_token":"d8fab905-a349-4731-b4e3-dcca75de9422","expires_at":"2025-12-24T00:56:38.958+00:00","paid_at":null,"dispensed_at":null,"customer_phone":null,"notes":null,"created_at":"2025-12-24T00:41:39.334896+00:00","updated_at":"2025-12-24T00:41:46.018+00:00","payments":[{"status":"PENDING","payment_type":"midtrans"}]}]}